detapack/__init__.py
detapack/main.py
detapack/utils.py
detapack-0.1.3.dist-info/METADATA
detapack-0.1.3.dist-info/WHEEL
detapack-0.1.3.dist-info/entry_points.txt
detapack-0.1.3.dist-info/RECORD
