Metadata-Version: 2.1
Name: detapack
Version: 0.1.3
Summary: 
Author: Paul Haedrich
Author-email: hey@foerstal.com
Requires-Python: >=3.9,<4.0
Classifier: Programming Language :: Python :: 3
Classifier: Programming Language :: Python :: 3.9
Classifier: Programming Language :: Python :: 3.10
Classifier: Programming Language :: Python :: 3.11
Requires-Dist: deta (>=1.2.0,<2.0.0)
Requires-Dist: rich (>=13.5.3,<14.0.0)
Requires-Dist: typer (>=0.9.0,<0.10.0)
